{
  "$schema": "https://developer.microsoft.com/json-schemas/spfx-build/package-solution.schema.json",
  "solution": {
    "name": "demsprofile-client-side-solution",
    "id": "9ed83f7c-b676-483a-85df-5dc5687a8175",
    "version": "1.0.0.0",
    "includeClientSideAssets": true,
    "skipFeatureDeployment": false,
    "isDomainIsolated": false,
    "developer": {
      "name": "",
      "websiteUrl": "",
      "privacyUrl": "",
      "termsOfUseUrl": "",
      "mpnId": ""
    }
  },
  "paths": {
    "zippedPackage": "solution/demsprofile.sppkg"
  }
}
